README.md
setup.py
src/milliluk/__init__.py
src/milliluk/cgp220/__init__.py
src/milliluk/cgp220/cgp220.py
src/milliluk/max2png/__init__.py
src/milliluk/max2png/max2png.py
src/milliluk_tools.egg-info/PKG-INFO
src/milliluk_tools.egg-info/SOURCES.txt
src/milliluk_tools.egg-info/dependency_links.txt
src/milliluk_tools.egg-info/entry_points.txt
src/milliluk_tools.egg-info/requires.txt
src/milliluk_tools.egg-info/top_level.txt