Metadata-Version: 2.1
Name: milliluk-tools
Version: 0.1
Summary: TRS-80 Color Computer Tools
Home-page: https://github.com/milliluk/milliluk-tools
Author: Erik Gavriluk
License: CC BY-NC-ND 4.0
Keywords: coco image conversion trs-80 tandy
Platform: UNKNOWN
Classifier: Development Status :: 3 - Alpha
Classifier: Intended Audience :: Developers
Classifier: Topic :: Software Development :: Build Tools
Classifier: License :: OSI Approved :: MIT License
Classifier: Programming Language :: Python :: 3
Requires-Python: >=3.3
Provides-Extra: test
